src/__init__.py
src/console.py
src/crypto.py
src/main.py
api_keychain-0.6.1.dist-info/entry_points.txt
api_keychain-0.6.1.dist-info/WHEEL
api_keychain-0.6.1.dist-info/METADATA
api_keychain-0.6.1.dist-info/RECORD
