Metadata-Version: 2.1
Name: api-keychain
Version: 0.6.1
Summary: A tool to manage API keys in a secure keychain
Home-page: https://github.com/nothead31/api-keychain
License: GPL-3.0-only
Keywords: api,keychain,security,development,password-manager
Author: Chris Trenthem
Author-email: trenthemc@gmail.com
Requires-Python: >=3.9,<4.0
Classifier: Development Status :: 1 - Planning
Classifier: Environment :: Console
Classifier: Intended Audience :: Developers
Classifier: Intended Audience :: Information Technology
Classifier: Intended Audience :: System Administrators
Classifier: License :: OSI Approved :: GNU General Public License v3 (GPLv3)
Classifier: Natural Language :: English
Classifier: Operating System :: OS Independent
Classifier: Programming Language :: Python :: 3
Classifier: Programming Language :: Python :: 3.9
Classifier: Topic :: Software Development
Requires-Dist: click (>=8.0.1,<9.0.0)
Requires-Dist: cryptography (>=3.4.7,<4.0.0)
Requires-Dist: passlib (>=1.7.4,<2.0.0)
Requires-Dist: pathlib (>=1.0.1,<2.0.0)
Requires-Dist: stdiomask (>=0.0.6,<0.0.7)
Requires-Dist: tinydb (>=4.5.1,<5.0.0)
Project-URL: Repository, https://github.com/nothead31/api-keychain
